[
  {"question":"Qual é o maior país do mundo em área territorial?","answer":"Rússia","options":["China","Estados Unidos","Rússia"]},
  {"question":"Qual é a fórmula da água?","answer":"H2O","options":["H2O","CO2","O2"]},
  {"question":"Qual é o planeta mais próximo do Sol?","answer":"Mercúrio","options":["Vênus","Mercúrio","Terra"]},
  {"question":"Quem escreveu 'Dom Quixote'?","answer":"Miguel de Cervantes","options":["Miguel de Cervantes","Gabriel García Márquez","Julio Cortázar"]},
  {"question":"Qual é a capital da França?","answer":"Paris","options":["Paris","Roma","Madri"]}
]
